dhxdocs/quickstart.py
dhxpyt/__init__.py
dhxpyt/gpu.py
dhxpyt/theme.py
dhxpyt/calendar/__init__.py
dhxpyt/calendar/calendar.py
dhxpyt/calendar/calendar_config.py
dhxpyt/cardflow/__init__.py
dhxpyt/cardflow/cardflow.py
dhxpyt/cardflow/cardflow_config.py
dhxpyt/cardpanel/__init__.py
dhxpyt/cardpanel/cardpanel.py
dhxpyt/cardpanel/cardpanel_config.py
dhxpyt/chart/__init__.py
dhxpyt/chart/chart.py
dhxpyt/chart/chart_config.py
dhxpyt/chat/__init__.py
dhxpyt/chat/chat.py
dhxpyt/chat/chat_config.py
dhxpyt/colorpicker/__init__.py
dhxpyt/colorpicker/colorpicker.py
dhxpyt/colorpicker/colorpicker_config.py
dhxpyt/combobox/__init__.py
dhxpyt/combobox/combobox.py
dhxpyt/combobox/combobox_config.py
dhxpyt/dhxsrc/cardflow.js
dhxpyt/dhxsrc/cardpanel.js
dhxpyt/dhxsrc/chat.js
dhxpyt/dhxsrc/dhx_custom.css
dhxpyt/dhxsrc/kanban.css
dhxpyt/dhxsrc/kanban.d.ts
dhxpyt/dhxsrc/kanban.js
dhxpyt/dhxsrc/kanban_board.js
dhxpyt/dhxsrc/license.txt
dhxpyt/dhxsrc/ragwidget.js
dhxpyt/dhxsrc/suite.css
dhxpyt/dhxsrc/suite.css.map
dhxpyt/dhxsrc/suite.d.ts
dhxpyt/dhxsrc/suite.js
dhxpyt/dhxsrc/suite.js.map
dhxpyt/dhxsrc/theme.js
dhxpyt/dhxsrc/webgpu.js
dhxpyt/dhxsrc/fonts/roboto-bold-webfont.woff
dhxpyt/dhxsrc/fonts/roboto-bold-webfont.woff2
dhxpyt/dhxsrc/fonts/roboto-medium-webfont.woff
dhxpyt/dhxsrc/fonts/roboto-medium-webfont.woff2
dhxpyt/dhxsrc/fonts/roboto-regular-webfont.woff
dhxpyt/dhxsrc/fonts/roboto-regular-webfont.woff2
dhxpyt/form/__init__.py
dhxpyt/form/form.py
dhxpyt/form/form_config.py
dhxpyt/form/controls/__init__.py
dhxpyt/form/controls/avatar.py
dhxpyt/form/controls/avatar_config.py
dhxpyt/form/controls/button.py
dhxpyt/form/controls/button_config.py
dhxpyt/form/controls/checkbox.py
dhxpyt/form/controls/checkbox_config.py
dhxpyt/form/controls/checkboxgroup.py
dhxpyt/form/controls/checkboxgroup_config.py
dhxpyt/form/controls/colorpicker.py
dhxpyt/form/controls/colorpicker_config.py
dhxpyt/form/controls/combo.py
dhxpyt/form/controls/combo_config.py
dhxpyt/form/controls/container.py
dhxpyt-0.9.12.dist-info/METADATA
dhxpyt-0.9.12.dist-info/WHEEL
dhxpyt-0.9.12.dist-info/top_level.txt
dhxpyt-0.9.12.dist-info/RECORD
