Metadata-Version: 2.4
Name: dhxpyt
Version: 0.9.12
Summary: Python wrapper for DHTMLX widgets
License: GNU General Public License v2
Project-URL: homepage, https://github.com/pytincture/dhx_pytincture_widgetset
Keywords: DHTMLX,widgetset
Requires-Python: >=3.12
Requires-Dist: pyodide-py>=0.28.0
Requires-Dist: itsdangerous>=2.2.0
